<?xml version="1.0"?>
<houses>
	<house name="Senja I" houseid="1" entryx="911" entryy="1054" entryz="7" rent="0" townid="5" size="27" />
	<house name="Senja II" houseid="2" entryx="908" entryy="1055" entryz="7" rent="0" townid="5" size="47" />
	<house name="Senja III" houseid="3" entryx="899" entryy="1050" entryz="7" rent="0" townid="5" size="49" />
	<house name="Senja IV" houseid="4" entryx="917" entryy="1038" entryz="7" rent="0" townid="5" size="19" />
	<house name="Senja V" houseid="5" entryx="918" entryy="1035" entryz="7" rent="0" townid="5" size="13" />
	<house name="Senja VI" houseid="6" entryx="922" entryy="1043" entryz="7" rent="0" townid="5" size="31" />
	<house name="Senja VII" houseid="7" entryx="927" entryy="1043" entryz="7" rent="0" townid="5" size="14" />
	<house name="Senja VIII" houseid="8" entryx="930" entryy="1040" entryz="6" rent="0" townid="5" size="25" />
	<house name="Senja IX" houseid="9" entryx="925" entryy="1034" entryz="6" rent="0" townid="5" size="13" />
	<house name="Senja X" houseid="10" entryx="899" entryy="1039" entryz="6" rent="0" townid="5" size="11" />
	<house name="" houseid="182" entryx="0" entryy="0" entryz="0" rent="0" townid="0" size="20" />
	<house name="" houseid="183" entryx="0" entryy="0" entryz="0" rent="0" townid="0" size="20" />
	<house name="" houseid="184" entryx="0" entryy="0" entryz="0" rent="0" townid="0" size="25" />
	<house name="" houseid="185" entryx="0" entryy="0" entryz="0" rent="0" townid="0" size="19" />
	<house name="" houseid="186" entryx="0" entryy="0" entryz="0" rent="0" townid="0" size="16" />
	<house name="" houseid="187" entryx="0" entryy="0" entryz="0" rent="0" townid="0" size="16" />
	<house name="" houseid="188" entryx="0" entryy="0" entryz="0" rent="0" townid="0" size="36" />
	<house name="" houseid="189" entryx="0" entryy="0" entryz="0" rent="0" townid="0" size="14" />
	<house name="" houseid="190" entryx="0" entryy="0" entryz="0" rent="0" townid="0" size="14" />
	<house name="" houseid="191" entryx="0" entryy="0" entryz="0" rent="0" townid="0" size="17" />
	<house name="" houseid="192" entryx="0" entryy="0" entryz="0" rent="0" townid="0" size="8" />
	<house name="" houseid="193" entryx="0" entryy="0" entryz="0" rent="0" townid="0" size="7" />
	<house name="" houseid="194" entryx="0" entryy="0" entryz="0" rent="0" townid="0" size="7" />
	<house name="" houseid="195" entryx="0" entryy="0" entryz="0" rent="0" townid="0" size="6" />
	<house name="" houseid="197" entryx="0" entryy="0" entryz="0" rent="0" townid="0" size="164" />
	<house name="" houseid="198" entryx="0" entryy="0" entryz="0" rent="0" townid="0" size="39" />
	<house name="" houseid="199" entryx="0" entryy="0" entryz="0" rent="0" townid="0" size="20" />
	<house name="" houseid="201" entryx="0" entryy="0" entryz="0" rent="0" townid="0" size="236" />
	<house name="" houseid="202" entryx="0" entryy="0" entryz="0" rent="0" townid="0" size="192" />
	<house name="" houseid="203" entryx="0" entryy="0" entryz="0" rent="0" townid="0" size="76" />
	<house name="" houseid="204" entryx="0" entryy="0" entryz="0" rent="0" townid="0" size="10" />
	<house name="" houseid="205" entryx="0" entryy="0" entryz="0" rent="0" townid="0" size="10" />
	<house name="" houseid="206" entryx="0" entryy="0" entryz="0" rent="0" townid="0" size="6" />
	<house name="" houseid="207" entryx="0" entryy="0" entryz="0" rent="0" townid="0" size="6" />
	<house name="" houseid="208" entryx="0" entryy="0" entryz="0" rent="0" townid="0" size="7" />
	<house name="" houseid="209" entryx="0" entryy="0" entryz="0" rent="0" townid="0" size="7" />
	<house name="" houseid="210" entryx="0" entryy="0" entryz="0" rent="0" townid="0" size="7" />
	<house name="" houseid="211" entryx="0" entryy="0" entryz="0" rent="0" townid="0" size="7" />
	<house name="" houseid="212" entryx="0" entryy="0" entryz="0" rent="0" townid="0" size="13" />
	<house name="" houseid="213" entryx="0" entryy="0" entryz="0" rent="0" townid="0" size="16" />
	<house name="" houseid="214" entryx="0" entryy="0" entryz="0" rent="0" townid="0" size="7" />
	<house name="" houseid="215" entryx="0" entryy="0" entryz="0" rent="0" townid="0" size="12" />
	<house name="" houseid="216" entryx="0" entryy="0" entryz="0" rent="0" townid="0" size="12" />
	<house name="" houseid="217" entryx="0" entryy="0" entryz="0" rent="0" townid="0" size="10" />
	<house name="" houseid="218" entryx="0" entryy="0" entryz="0" rent="0" townid="0" size="2" />
	<house name="" houseid="219" entryx="0" entryy="0" entryz="0" rent="0" townid="0" size="10" />
	<house name="" houseid="220" entryx="0" entryy="0" entryz="0" rent="0" townid="0" size="10" />
	<house name="" houseid="221" entryx="0" entryy="0" entryz="0" rent="0" townid="0" size="2" />
	<house name="" houseid="222" entryx="0" entryy="0" entryz="0" rent="0" townid="0" size="10" />
	<house name="" houseid="223" entryx="0" entryy="0" entryz="0" rent="0" townid="0" size="47" />
	<house name="" houseid="224" entryx="0" entryy="0" entryz="0" rent="0" townid="0" size="34" />
	<house name="" houseid="225" entryx="0" entryy="0" entryz="0" rent="0" townid="0" size="89" />
	<house name="" houseid="227" entryx="0" entryy="0" entryz="0" rent="0" townid="0" size="33" />
	<house name="" houseid="228" entryx="0" entryy="0" entryz="0" rent="0" townid="0" size="40" />
	<house name="" houseid="229" entryx="0" entryy="0" entryz="0" rent="0" townid="0" size="11" />
	<house name="" houseid="230" entryx="0" entryy="0" entryz="0" rent="0" townid="0" size="10" />
	<house name="" houseid="231" entryx="0" entryy="0" entryz="0" rent="0" townid="0" size="10" />
	<house name="" houseid="232" entryx="0" entryy="0" entryz="0" rent="0" townid="0" size="15" />
	<house name="" houseid="233" entryx="0" entryy="0" entryz="0" rent="0" townid="0" size="15" />
	<house name="" houseid="235" entryx="0" entryy="0" entryz="0" rent="0" townid="0" size="7" />
	<house name="" houseid="236" entryx="0" entryy="0" entryz="0" rent="0" townid="0" size="7" />
	<house name="" houseid="237" entryx="0" entryy="0" entryz="0" rent="0" townid="0" size="7" />
	<house name="" houseid="238" entryx="0" entryy="0" entryz="0" rent="0" townid="0" size="7" />
	<house name="" houseid="239" entryx="0" entryy="0" entryz="0" rent="0" townid="0" size="4" />
	<house name="" houseid="240" entryx="0" entryy="0" entryz="0" rent="0" townid="0" size="6" />
	<house name="" houseid="241" entryx="0" entryy="0" entryz="0" rent="0" townid="0" size="8" />
	<house name="" houseid="242" entryx="0" entryy="0" entryz="0" rent="0" townid="0" size="6" />
	<house name="" houseid="243" entryx="0" entryy="0" entryz="0" rent="0" townid="0" size="6" />
	<house name="" houseid="244" entryx="0" entryy="0" entryz="0" rent="0" townid="0" size="4" />
	<house name="" houseid="245" entryx="0" entryy="0" entryz="0" rent="0" townid="0" size="6" />
	<house name="" houseid="246" entryx="0" entryy="0" entryz="0" rent="0" townid="0" size="6" />
	<house name="" houseid="247" entryx="0" entryy="0" entryz="0" rent="0" townid="0" size="8" />
	<house name="" houseid="248" entryx="0" entryy="0" entryz="0" rent="0" townid="0" size="6" />
	<house name="" houseid="249" entryx="0" entryy="0" entryz="0" rent="0" townid="0" size="6" />
	<house name="" houseid="250" entryx="0" entryy="0" entryz="0" rent="0" townid="0" size="8" />
	<house name="" houseid="251" entryx="0" entryy="0" entryz="0" rent="0" townid="0" size="20" />
	<house name="" houseid="252" entryx="0" entryy="0" entryz="0" rent="0" townid="0" size="18" />
	<house name="" houseid="253" entryx="0" entryy="0" entryz="0" rent="0" townid="0" size="19" />
	<house name="" houseid="254" entryx="0" entryy="0" entryz="0" rent="0" townid="0" size="4" />
	<house name="" houseid="255" entryx="0" entryy="0" entryz="0" rent="0" townid="0" size="7" />
	<house name="" houseid="256" entryx="0" entryy="0" entryz="0" rent="0" townid="0" size="7" />
	<house name="" houseid="257" entryx="0" entryy="0" entryz="0" rent="0" townid="0" size="7" />
	<house name="" houseid="258" entryx="0" entryy="0" entryz="0" rent="0" townid="0" size="15" />
	<house name="" houseid="259" entryx="0" entryy="0" entryz="0" rent="0" townid="0" size="15" />
	<house name="" houseid="276" entryx="0" entryy="0" entryz="0" rent="0" townid="0" size="0" />
	<house name="" houseid="277" entryx="0" entryy="0" entryz="0" rent="0" townid="0" size="0" />
	<house name="" houseid="279" entryx="0" entryy="0" entryz="0" rent="0" townid="0" size="253" />
	<house name="" houseid="825" entryx="0" entryy="0" entryz="0" rent="0" townid="0" size="122" />
	<house name="" houseid="826" entryx="0" entryy="0" entryz="0" rent="0" townid="0" size="194" />
	<house name="" houseid="827" entryx="0" entryy="0" entryz="0" rent="0" townid="0" size="56" />
	<house name="" houseid="837" entryx="0" entryy="0" entryz="0" rent="0" townid="0" size="8" />
	<house name="" houseid="838" entryx="0" entryy="0" entryz="0" rent="0" townid="0" size="8" />
	<house name="" houseid="839" entryx="0" entryy="0" entryz="0" rent="0" townid="0" size="8" />
	<house name="" houseid="840" entryx="0" entryy="0" entryz="0" rent="0" townid="0" size="23" />
	<house name="" houseid="841" entryx="0" entryy="0" entryz="0" rent="0" townid="0" size="10" />
	<house name="" houseid="964" entryx="0" entryy="0" entryz="0" rent="0" townid="0" size="87" />
</houses>
